huaweicloudsdkfgs/__init__.py
huaweicloudsdkfgs/v2/__init__.py
huaweicloudsdkfgs/v2/fgs_async_client.py
huaweicloudsdkfgs/v2/fgs_client.py
huaweicloudsdkfgs/v2/model/__init__.py
huaweicloudsdkfgs/v2/model/async_invoke_function_request.py
huaweicloudsdkfgs/v2/model/async_invoke_function_response.py
huaweicloudsdkfgs/v2/model/batch_delete_function_triggers_request.py
huaweicloudsdkfgs/v2/model/batch_delete_function_triggers_response.py
huaweicloudsdkfgs/v2/model/create_function_request.py
huaweicloudsdkfgs/v2/model/create_function_request_body.py
huaweicloudsdkfgs/v2/model/create_function_response.py
huaweicloudsdkfgs/v2/model/create_function_trigger_request.py
huaweicloudsdkfgs/v2/model/create_function_trigger_request_body.py
huaweicloudsdkfgs/v2/model/create_function_trigger_response.py
huaweicloudsdkfgs/v2/model/create_function_version_request.py
huaweicloudsdkfgs/v2/model/create_function_version_request_body.py
huaweicloudsdkfgs/v2/model/create_function_version_response.py
huaweicloudsdkfgs/v2/model/create_version_alias_request.py
huaweicloudsdkfgs/v2/model/create_version_alias_request_body.py
huaweicloudsdkfgs/v2/model/create_version_alias_response.py
huaweicloudsdkfgs/v2/model/delete_function_request.py
huaweicloudsdkfgs/v2/model/delete_function_response.py
huaweicloudsdkfgs/v2/model/delete_function_trigger_request.py
huaweicloudsdkfgs/v2/model/delete_function_trigger_response.py
huaweicloudsdkfgs/v2/model/delete_version_alias_request.py
huaweicloudsdkfgs/v2/model/delete_version_alias_response.py
huaweicloudsdkfgs/v2/model/dependency.py
huaweicloudsdkfgs/v2/model/func_code.py
huaweicloudsdkfgs/v2/model/func_mount.py
huaweicloudsdkfgs/v2/model/func_vpc.py
huaweicloudsdkfgs/v2/model/invoke_function_request.py
huaweicloudsdkfgs/v2/model/invoke_function_response.py
huaweicloudsdkfgs/v2/model/list_function_result.py
huaweicloudsdkfgs/v2/model/list_function_trigger_result.py
huaweicloudsdkfgs/v2/model/list_function_triggers_request.py
huaweicloudsdkfgs-3.0.8b0.dist-info/LICENSE
huaweicloudsdkfgs-3.0.8b0.dist-info/METADATA
huaweicloudsdkfgs-3.0.8b0.dist-info/WHEEL
huaweicloudsdkfgs-3.0.8b0.dist-info/top_level.txt
huaweicloudsdkfgs-3.0.8b0.dist-info/RECORD
